{
  "questionId": "Q9642",
  "title": "Chef And Adjacent Sums",
  "slug": "chef-and-adjacent-sums",
  "version": 1,
  "createdAt": "2026-07-02",
  "updatedAt": "2026-07-02",
  "metadata": {
    "category": "Arrays",
    "difficulty": "Medium",
    "isPremium": true,
    "tags": [
      "constructive algorithms",
      "competitive programming"
    ],
    "companyTags": [],
    "topicTags": [
      "Constructive Algorithms"
    ],
    "QBCategory": "CCD"
  },
  "content": {
    "problemStatement": "You are given an array AAA of size NNN.\n\nConsider an array BBB of size NNN formed by sorting AAA in non-decreasing order.\n\nLet Z=(BN+B(N−1))Z = (B_N + B_{(N-1)})Z=(BN​+B(N−1)​).\n\nFind whether there exists any rearrangement of the array AAA, such that, for all (1≤i&lt;N)(1\\le i \\lt N)(1≤i&lt;N),\n\n(Ai+A(i+1))&lt;Z(A_i + A_{(i+1)}) \\lt Z(Ai​+A(i+1)​)&lt;Z.\n\nIf such a rearrangement exists, print `YES`, otherwise print `NO`.\n\n\nInput Format\n\nThe first line of input will contain a single integer TTT, denoting the number of test cases.\nEach test case consists of multiple lines of input.\n\nThe first line of each test case contains a integer NNN  — the number of elements in the array.\nThe next line contains NNN space-separated integers, denoting the elements of the array.\n\n\n\n\nOutput Format\nFor each test case, output `YES`, if a rearrangement exists that satisfies the conditions. Otherwise, output `NO`.\n\n\nYou may print each character in uppercase or lowercase. For example, `NO`, `no`, `No`, and `nO` are all considered the same.",
    "constraints": [
      "1≤T≤10001 \\leq T \\leq 10001≤T≤1000",
      "2≤N≤1052 \\leq N \\leq 10^52≤N≤105",
      "1≤Ai≤1051 \\leq A_i \\leq 10^51≤Ai​≤105",
      "The sum of NNN over all test cases won't exceed 10510^5105."
    ],
    "inputFormat": "",
    "outputFormat": "",
    "sampleTestCases": [
      {
        "id": "sample_1",
        "input": "4\n3\n3 4 4\n4\n1 2 3 4\n2\n2 2\n2\n1 2",
        "output": "YES\nYES\nNO\nNO",
        "explanation": "Explanation:\nTest case 111: Here B=[3,4,4]B = [3, 4, 4]B=[3,4,4] and Z=(4+4)=8Z = (4 + 4) = 8Z=(4+4)=8.\nWe can rearrange the array to [4,3,4][4,3,4][4,3,4] such that (A1+A2)=7<8(A_1 + A_2) = 7 \\lt 8(A1​+A2​)=7<8 and (A2+A3)=7<8(A_2 + A_3) = 7 \\lt 8(A2​+A3​)=7<8. Thus, the rearrangement is valid.\nTest case 222: Here B=[1,2,3,4]B = [1, 2, 3, 4]B=[1,2,3,4] and Z=(4+3)=7Z = (4 + 3) = 7Z=(4+3)=7.\nWe can rearrange the array to [4,2,3,1][4,2,3,1][4,2,3,1] such that (A1+A2)=6<7(A_1 + A_2) = 6 \\lt 7(A1​+A2​)=6<7, (A2+A3)=5<7(A_2 + A_3) = 5 \\lt 7(A2​+A3​)=5<7, and (A3+A4)=4<7(A_3 + A_4) = 4 \\lt 7(A3​+A4​)=4<7. Thus, the rearrangement is valid.\nTest case 333: The exists no possible rearrangement that satisfies the conditions.\nTest case 444: The exists no possible rearrangement that satisfies the conditions."
      }
    ]
  },
  "testCases": {
    "hidden": [
      {
        "id": "tc_1",
        "input": "4\n3\n3 4 4\n4\n1 2 3 4\n2\n2 2\n2\n1 2",
        "expectedOutput": "YES\nYES\nNO\nNO",
        "weight": 100
      }
    ],
    "totalTestCases": 1,
    "totalWeight": 100
  },
  "scoring": {
    "defaultScoringType": "PARTIAL_SCORE",
    "testCaseWeights": [
      100
    ],
    "maxScore": 100
  },
  "judging": {
    "timeLimitMs": 2000,
    "memoryLimitMb": 256,
    "supportedLanguages": [
      "C",
      "C++",
      "Java",
      "Python3",
      "JavaScript"
    ]
  },
  "solution": {
    "approach": "**Observations:**\n\n\nZ is the sum of the two largest elements in the array.\nTo satisfy the condition (A[i]+A[i+1])&lt;Z for all i, the rearrangement should avoid placing the two largest elements next to each other.\nThe frequency of the largest or second-largest elements must not dominate the array, as it would force them to be adjacent.\n**Special Cases:**\n\n\nIf the largest element occurs too many times (more than half of N), it is impossible to avoid adjacency.\n**Plan:**\n\n\nSort the array A to compute Z.\nCheck the frequency of the largest element. If it appears more than ⌈N/2⌉ times, output “NO”.\nOtherwise, check the adjacency condition using frequency analysis of the largest and second-largest elements.",
    "timeComplexity": "Sorting takes O(N log ⁡N). Frequency Count takes O(N). Overall Complexity will come as O(N log ⁡N).",
    "spaceComplexity": "* A map (or unordered_map) is used to store the frequency of elements. In the worst case, all elements are unique, so the map requires O(N) space for N key-value pairs.",
    "code": {}
  },
  "QBCategory": "CCD",
  "boilerPlates": {
    "C": "#include <stdio.h>\n\nint main() {\n    // your code goes here\n    return 0;\n}",
    "C++": "#include <iostream>\nusing namespace std;\n\nint main() {\n    // your code goes here\n    return 0;\n}",
    "Java": "import java.util.*;\nimport java.io.*;\n\npublic class Main {\n    public static void main(String[] args) throws IOException {\n        // your code goes here\n    }\n}",
    "Python3": "# your code goes here\n",
    "JavaScript": "// your code goes here\n"
  },
  "_internal": {
    "methodName": "",
    "params": []
  }
}