{
  "questionId": "Q4518",
  "title": "Find Peak Element",
  "slug": "find-peak-element",
  "version": 1,
  "createdAt": "2026-07-01",
  "updatedAt": "2026-07-12",
  "metadata": {
    "category": "Searching",
    "difficulty": "Medium",
    "isPremium": false,
    "tags": [
      "Binary Search",
      "Array"
    ],
    "companyTags": [],
    "topicTags": [
      "Binary Search"
    ],
    "QBCategory": "CCD"
  },
  "content": {
    "problemStatement": "A **peak element** in an array is an element that is **strictly greater** than its adjacent elements.\n\nYou are provided with a **0-based index integer array** numsnumsnums of size NNN. Your task is to identify the index of **any one peak element** in the array and return it. If multiple peak elements exist, returning the index of any one of them is acceptable.\n\nFor simplicity, assume that the elements just outside the boundaries of the array are considered to be negative infinity. That is:\n\n\narr[−1]=−∞arr[-1] = -∞arr[−1]=−∞\narr[arr.length]=−∞arr[arr.length] = -∞arr[arr.length]=−∞\nYour solution **must have a time complexity of O(log N).**\n\nFunction DeclarationFunction NamefindPeakElementfindPeakElementfindPeakElement – This function finds the index of a peak element in the array.\n\nParameters\nnumsnumsnums : A 0-based indexed array of integers where adjacent elements are not equal.\nReturn Value\nReturns a single integer — the **index of any peak element**.\nConstraints\n1≤T≤10001 \\leq T \\leq 10001≤T≤1000\n1≤N≤10001 \\leq N \\leq 10001≤N≤1000\n−231≤nums[i]≤231−1−2^\\text{31} \\leq nums[i] \\leq 2^\\text{31} − 1−231≤nums[i]≤231−1\nnums[i]≠nums[i+1]nums[i] ≠ nums[i + 1]nums[i]=nums[i+1] for all valid indices iii\nTime complexity must be **O(log n)**\n\nInput Format\n\nThe first line contains the number of test cases TTT \n\nEach test case contains:\n\nThe first line contains a single integer NNN — the size of the array.\nThe second line contains NNN space-separated integers representing the array elements.\n\n\n\n\nOutput Format\n\nPrint a single integer — the index of a peak element.",
    "constraints": [
      "1 <= T <= 1000",
      "1 <= N <= 1000",
      "-2^31 <= nums[i] <= 2^31-1",
      "nums[i] != nums[i+1] for all valid i"
    ],
    "inputFormat": "First line contains an integer T, the number of test cases. For each test case: first line contains integer N, the size of the array. Second line contains N space‑separated integers representing the array. All indices are 0‑based.",
    "outputFormat": "For each test case output a single line containing the 0‑based index of any peak element in the given array.",
    "sampleTestCases": [
      {
        "id": "sample_1",
        "input": "2\n5\n5 10 7 3 8\n5\n2 4 3 6 1",
        "output": "1\n3",
        "explanation": "First array: 10 at index 1 is a peak (10 > 5 and 10 > 7). Second array: 6 at index 3 is a peak (6 > 3 and 6 > 1). The binary‑search may also return other valid peaks, but the shown indices satisfy the requirement."
      },
      {
        "id": "sample_2",
        "input": "1\n5\n1 2 3 4 5",
        "output": "4",
        "explanation": "The array is strictly increasing, so the last element (5) is a peak because the virtual element after it is -∞."
      },
      {
        "id": "sample_3",
        "input": "1\n5\n5 4 3 2 1",
        "output": "0",
        "explanation": "The array is strictly decreasing, so the first element (5) is a peak because the virtual element before it is -∞."
      }
    ]
  },
  "testCases": {
    "hidden": [
      {
        "id": "tc_1",
        "label": "minimum boundary",
        "input": "1\n1\n0",
        "expectedOutput": "0",
        "weight": 1
      },
      {
        "id": "tc_2",
        "label": "minimum boundary 2",
        "input": "1\n1\n-2147483648",
        "expectedOutput": "0",
        "weight": 1
      },
      {
        "id": "tc_3",
        "label": "minimum boundary 3",
        "input": "1\n2\n-5 5",
        "expectedOutput": "1",
        "weight": 1
      },
      {
        "id": "tc_4",
        "label": "minimum boundary 4",
        "input": "1\n2\n5 -5",
        "expectedOutput": "0",
        "weight": 1
      },
      {
        "id": "tc_5",
        "label": "maximum boundary",
        "input": "1\n15\n2147483646 -2147483647 2147483645 -2147483646 2147483644 -2147483645 2147483643 -2147483644 2147483642 -2147483643 2147483641 -2147483642 2147483640 -2147483641 2147483639",
        "expectedOutput": "14",
        "weight": 1
      },
      {
        "id": "tc_6",
        "label": "maximum boundary 2",
        "input": "1\n15\n-2147483648 2147483647 -2147483647 2147483646 -2147483646 2147483645 -2147483645 2147483644 -2147483644 2147483643 -2147483643 2147483642 -2147483642 2147483641 -2147483641",
        "expectedOutput": "1",
        "weight": 1
      },
      {
        "id": "tc_7",
        "label": "maximum boundary 3",
        "input": "1\n10\n1000000000 -1000000000 999999999 -999999999 999999998 -999999998 999999997 -999999997 999999996 -999999996",
        "expectedOutput": "2",
        "weight": 1
      },
      {
        "id": "tc_8",
        "label": "maximum boundary 4",
        "input": "1\n8\n-1 2 -3 4 -5 6 -7 8",
        "expectedOutput": "1",
        "weight": 1
      },
      {
        "id": "tc_9",
        "label": "uniform case",
        "input": "1\n5\n7 7 7 7 7",
        "expectedOutput": "4",
        "weight": 1
      },
      {
        "id": "tc_10",
        "label": "uniform case 2",
        "input": "1\n4\n-3 -3 -3 -3",
        "expectedOutput": "3",
        "weight": 1
      },
      {
        "id": "tc_11",
        "label": "structured case",
        "input": "1\n6\n1 3 5 7 9 11",
        "expectedOutput": "5",
        "weight": 1
      },
      {
        "id": "tc_12",
        "label": "structured case 2",
        "input": "1\n6\n11 9 7 5 3 1",
        "expectedOutput": "0",
        "weight": 1
      },
      {
        "id": "tc_13",
        "label": "tricky case",
        "input": "1\n7\n2 1 2 3 4 5 6",
        "expectedOutput": "6",
        "weight": 1
      },
      {
        "id": "tc_14",
        "label": "tricky case 2",
        "input": "1\n7\n6 5 4 3 2 1 2",
        "expectedOutput": "0",
        "weight": 1
      },
      {
        "id": "tc_15",
        "label": "tricky case 3",
        "input": "1\n9\n0 2 1 3 2 4 3 5 4",
        "expectedOutput": "7",
        "weight": 1
      },
      {
        "id": "tc_16",
        "label": "tricky case 4",
        "input": "1\n9\n4 5 4 3 2 1 0 -1 -2",
        "expectedOutput": "1",
        "weight": 1
      },
      {
        "id": "tc_17",
        "label": "stress case",
        "input": "3\n3\n1 3 2\n4\n4 1 2 3\n5\n5 1 2 3 4",
        "expectedOutput": "1\n3\n4",
        "weight": 1
      },
      {
        "id": "tc_18",
        "label": "stress case 2",
        "input": "2\n6\n-10 -5 -1 0 5 10\n6\n10 5 0 -1 -5 -10",
        "expectedOutput": "5\n0",
        "weight": 1
      },
      {
        "id": "tc_19",
        "label": "stress case 3",
        "input": "4\n1\n42\n2\n-1 1\n3\n-2 0 2\n4\n3 2 1 0",
        "expectedOutput": "0\n1\n2\n0",
        "weight": 1
      },
      {
        "id": "tc_20",
        "label": "stress case 4",
        "input": "2\n8\n1 2 3 4 5 6 7 8\n8\n8 7 6 5 4 3 2 1",
        "expectedOutput": "7\n0",
        "weight": 1
      }
    ],
    "totalTestCases": 20,
    "totalWeight": 20
  },
  "scoring": {
    "defaultScoringType": "PARTIAL_SCORE",
    "testCaseWeights": [
      1,
      1,
      1,
      1,
      1,
      1,
      1,
      1,
      1,
      1,
      1,
      1,
      1,
      1,
      1,
      1,
      1,
      1,
      1,
      1
    ],
    "maxScore": 20
  },
  "judging": {
    "timeLimitMs": 2000,
    "memoryLimitMb": 256,
    "supportedLanguages": [
      "C",
      "C++",
      "Java",
      "Python3",
      "JavaScript"
    ]
  },
  "solution": {
    "approach": "The problem can be solved with a classic binary‑search on the array. At any position mid, compare nums[mid] with its right neighbour nums[mid+1]. If nums[mid] > nums[mid+1] the peak lies on the left side (including mid) because the left side cannot be strictly increasing forever due to the -∞ boundary. Otherwise the peak lies on the right side (mid+1 onward). Repeating this shrinks the interval until left == right, which is a peak index. This runs in O(log N) time and O(1) extra space.",
    "timeComplexity": "O(log N) per test case, O(T log N) overall.",
    "spaceComplexity": "O(1) auxiliary space.",
    "code": {
      "C": "",
      "C++": "",
      "Java": "import java.io.*;\nimport java.util.*;\n\npublic class Main {\n    private static int findPeak(int[] nums) {\n        int left = 0, right = nums.length - 1;\n        while (left < right) {\n            int mid = left + (right - left) / 2;\n            if (nums[mid] > nums[mid + 1]) {\n                right = mid;\n            } else {\n                left = mid + 1;\n            }\n        }\n        return left;\n    }\n    public static void main(String[] args) throws Exception {\n        BufferedReader br = new BufferedReader(new InputStreamReader(System.in));\n        StringBuilder sb = new StringBuilder();\n        int T = Integer.parseInt(br.readLine().trim());\n        while (T-- > 0) {\n            int N = Integer.parseInt(br.readLine().trim());\n            int[] nums = new int[N];\n            StringTokenizer st = new StringTokenizer(br.readLine());\n            for (int i = 0; i < N; i++) {\n                nums[i] = Integer.parseInt(st.nextToken());\n            }\n            sb.append(findPeak(nums)).append('\\n');\n        }\n        System.out.print(sb.toString());\n    }\n}",
      "Python3": "",
      "JavaScript": ""
    }
  },
  "QBCategory": "CCD",
  "boilerPlates": {
    "C": "#include <stdio.h>\n\nint main() {\n    // your code goes here\n    return 0;\n}",
    "C++": "#include <iostream>\nusing namespace std;\n\nint main() {\n    // your code goes here\n    return 0;\n}",
    "Java": "import java.util.*;\nimport java.io.*;\n\npublic class Main {\n    public static void main(String[] args) throws IOException {\n        // your code goes here\n    }\n}",
    "Python3": "# your code goes here\n",
    "JavaScript": "// your code goes here\n"
  },
  "_internal": {
    "methodName": "",
    "params": []
  },
  "tcGeneratorPython": "def generate_case(i, RINT, POWER):\n    # i: test case index (1‑based as used in hiddenTestCases)\n    if i == 1:\n        print(1)\n        print(1)\n        print(0)\n    elif i == 2:\n        print(1)\n        print(1)\n        print(-2147483648)\n    elif i == 3:\n        print(1)\n        print(2)\n        print('-5 5')\n    elif i == 4:\n        print(1)\n        print(2)\n        print('5 -5')\n    elif i == 5:\n        print(1)\n        print(15)\n        arr = [2147483646, -2147483647, 2147483645, -2147483646, 2147483644, -2147483645,\n               2147483643, -2147483644, 2147483642, -2147483643, 2147483641, -2147483642,\n               2147483640, -2147483641, 2147483639]\n        print(' '.join(map(str, arr)))\n    elif i == 6:\n        print(1)\n        print(15)\n        arr = [-2147483648, 2147483647, -2147483647, 2147483646, -2147483646, 2147483645,\n               -2147483645, 2147483644, -2147483644, 2147483643, -2147483643, 2147483642,\n               -2147483642, 2147483641, -2147483641]\n        print(' '.join(map(str, arr)))\n    elif i == 7:\n        print(1)\n        print(10)\n        arr = [1000000000, -1000000000, 999999999, -999999999, 999999998, -999999998,\n               999999997, -999999997, 999999996, -999999996]\n        print(' '.join(map(str, arr)))\n    elif i == 8:\n        print(1)\n        print(8)\n        print('-1 2 -3 4 -5 6 -7 8')\n    elif i == 9:\n        print(1)\n        print(5)\n        print('7 7 7 7 7')\n    elif i == 10:\n        print(1)\n        print(4)\n        print('-3 -3 -3 -3')\n    elif i == 11:\n        print(1)\n        print(6)\n        print('1 3 5 7 9 11')\n    elif i == 12:\n        print(1)\n        print(6)\n        print('11 9 7 5 3 1')\n    elif i == 13:\n        print(1)\n        print(7)\n        print('2 1 2 3 4 5 6')\n    elif i == 14:\n        print(1)\n        print(7)\n        print('6 5 4 3 2 1 2')\n    elif i == 15:\n        print(1)\n        print(9)\n        print('0 2 1 3 2 4 3 5 4')\n    elif i == 16:\n        print(1)\n        print(9)\n        print('4 5 4 3 2 1 0 -1 -2')\n    elif i == 17:\n        print(3)\n        print(3)\n        print('1 3 2')\n        print(4)\n        print('4 1 2 3')\n        print(5)\n        print('5 1 2 3 4')\n    elif i == 18:\n        print(2)\n        print(6)\n        print('-10 -5 -1 0 5 10')\n        print(6)\n        print('10 5 0 -1 -5 -10')\n    elif i == 19:\n        print(4)\n        print(1)\n        print('42')\n        print(2)\n        print('-1 1')\n        print(3)\n        print('-2 0 2')\n        print(4)\n        print('3 2 1 0')\n    elif i == 20:\n        print(2)\n        print(8)\n        print('1 2 3 4 5 6 7 8')\n        print(8)\n        print('8 7 6 5 4 3 2 1')\n    else:\n        pass"
}