{
  "questionId": "Q6695",
  "title": "Flower Pots",
  "slug": "flower-pots",
  "version": 1,
  "createdAt": "2026-07-02",
  "updatedAt": "2026-07-04",
  "metadata": {
    "category": "Dynamic Programming",
    "difficulty": "Hard",
    "isPremium": true,
    "tags": [
      "Dynamic Programming",
      "Greedy",
      "Optimization"
    ],
    "companyTags": [],
    "topicTags": [
      "Dynamic Programming"
    ],
    "QBCategory": "CCD"
  },
  "content": {
    "problemStatement": "The Chef wants to celebrate Independence Day with fireworks. He's particularly fond of Flower Pot crackers (or Fountain fireworks) which spew out fire around them:\n\n\n\n\n\nHe's decided that he wants a row of **N** of these crackers. He has decided where exactly each of them will be placed. In particular, we can say that the crackers will be on a line with coordinates **A1**, **A2**, ..., **AN**.\n\nThese crackers come in many strengths. For any integer S ≥ 0, unlimited number of crackers of strength S are available for sale at the shop. The larger the strength of a cracker, the higher and wider it will spew fire. In particular, a cracker whose strength is s, and which is placed at coordinate X will spew fire everywhere in the interval [X - S, X + S], both end points inclusive. The cost of a cracker of strength S is S2.\n\nChef wants to decide what the strengths of each of the **N** crackers should be. He wants to light up only one of the **N** crackers, the **C**-th one, which is as coordinate **AC**. The other **N** - 1 crackers should light up automatically. That is, suppose the cracker at **AC** has a strength of S**C**, then it will light up any unlit cracker in the interval [**AC** - S**C**, **AC** + S**C**]. And these should then explode and light up more crackers, etc. This should continue until all the crackers are lit. Also, each cracker, once lit, takes 1 second to explode. Once it explodes, it instantaneously lights up all the unlit crackers in its interval. And Chef wants all the crackers to be lit up (not necessarily explode) within **B** seconds after he has lit **AC**. That is, if a cracker is lit up **B** seconds after he has lit **AC**, even though it has not exploded, Chef is happy with it, and it is valid.\n\nFind out the minimum amount Chef has to spend in buying the crackers so as to achieve his goals.",
    "constraints": [
      "1 ≤ T ≤ 5",
      "1 ≤ N ≤ 3000",
      "1 ≤ B ≤ 3000",
      "1 ≤ C ≤ N",
      "1 ≤ N * B ≤ 30000",
      "1 ≤ A1 < A2 < ... < AN ≤ 10^8"
    ],
    "inputFormat": "The first line of the input contains an integer T, denoting the number of test cases. The description of T test cases follows. The first line of each testcase contains three integers, N, B, and C, which denote the number of crackers, the time within which all the crackers should be lit up, and the index of the cracker which he will light up, respectively. The next line contains N integers: A1, A2, ..., AN.",
    "outputFormat": "For each test case, output a single line containing a single integer which should be the minimum total cost.",
    "sampleTestCases": [
      {
        "id": "sample_1",
        "input": "1\n5 2 4\n2 4 10 15 18",
        "output": "89",
        "explanation": "One optimal way is to choose the strengths of the crackers as (0, 0, 8, 5, 0). That is, the leftmost cracker has strength 0, the next has 0, the next has 8, etc. Now, Chef lights up the 4-th cracker. After 1 second, it explodes and it lights up all the unlit crackers in its interval. Because its strength is 5, its interval would be [15 - 5, 15 + 5] = [10, 20]. So after 1 second, the third and fifth cracker are also lit. After one more second (ie. 2 seconds from when Chef lit up the 4- cracker), those two explode. Because the fifth's strength is 0, it doesn't affect anything else. But the third cracker's strength is 8, and hence it lights up all unlit crackers in the interval [10 - 8, 10 + 8] = [2, 18]. Note that this includes all the crackers. Hence all the unlit crackers are lit up instantaneously, and so all the five crackers have been lit within 2 seconds of Chef lighting up the one cracker. Thus this is a valid configuration. Also note that the first and second crackers have only been lit, and they are yet to explode. But that is fine. The total cost of this is 0^2 + 0^2 + 8^2 + 5^2 + 0^2 = 89. You cannot get a lower cost, and hence this is the answer."
      }
    ]
  },
  "testCases": {
    "hidden": [
      {
        "id": "tc_1",
        "label": "minimum boundary",
        "input": "1\n1 1 1\n1",
        "expectedOutput": "0",
        "weight": 2
      },
      {
        "id": "tc_2",
        "label": "maximum boundary",
        "input": "1\n3000 3000 3000\n1 2 3 4 5 6 7 8 9 10 11 12 13 14 15 16 17 18 19 20 21 22 23 24 25 26 27 28 29 30",
        "expectedOutput": "3000^2",
        "weight": 2
      },
      {
        "id": "tc_3",
        "label": "edge case",
        "input": "1\n5 2 3\n1 2 3 4 5",
        "expectedOutput": "4",
        "weight": 2
      },
      {
        "id": "tc_4",
        "label": "general case 1",
        "input": "1\n10 5 5\n1 2 3 4 5 6 7 8 9 10",
        "expectedOutput": "25",
        "weight": 2
      },
      {
        "id": "tc_5",
        "label": "general case 2",
        "input": "1\n15 10 10\n1 2 3 4 5 6 7 8 9 10 11 12 13 14 15 16 17 18 19 20",
        "expectedOutput": "100",
        "weight": 2
      }
    ],
    "totalTestCases": 5,
    "totalWeight": 10
  },
  "scoring": {
    "defaultScoringType": "PARTIAL_SCORE",
    "testCaseWeights": [
      2,
      2,
      2,
      2,
      2
    ],
    "maxScore": 10
  },
  "judging": {
    "timeLimitMs": 2000,
    "memoryLimitMb": 256,
    "supportedLanguages": [
      "C",
      "C++",
      "Java",
      "Python3",
      "JavaScript"
    ]
  },
  "solution": {
    "approach": "To solve this problem, we can use dynamic programming to find the minimum cost for each cracker. We start by initializing the cost for the first cracker to 0. Then, for each subsequent cracker, we calculate the minimum cost by considering all possible strengths for the current cracker and choosing the one that results in the minimum total cost. We also need to ensure that the crackers are lit up within the given time limit B.",
    "timeComplexity": "O(T * N^2 * B) — The time complexity is dominated by the three nested loops over T test cases, N crackers, and B time limit.",
    "spaceComplexity": "O(N) — The space complexity is dominated by the array used to store the costs for each cracker.",
    "code": {
      "C": "#include <stdio.h>\n#include <limits.h>\nint main() {\n    int T;\n    scanf(\"%d\", &T);\n    while (T--) {\n        int N, B, C;\n        scanf(\"%d %d %d\", &N, &B, &C);\n        int A[N];\n        for (int i = 0; i < N; i++) {\n            scanf(\"%d\", &A[i]);\n        }\n        long long dp[N];\n        for (int i = 0; i < N; i++) {\n            dp[i] = LLONG_MAX;\n        }\n        dp[C - 1] = 0;\n        for (int i = 0; i < B; i++) {\n            for (int j = 0; j < N; j++) {\n                if (dp[j] != LLONG_MAX) {\n                    for (int k = 0; k < N; k++) {\n                        if (A[k] >= A[j] - i - 1 && A[k] <= A[j] + i + 1) {\n                            dp[k] = (dp[k] < dp[j] + (i + 1) * (i + 1)) ? dp[k] : dp[j] + (i + 1) * (i + 1);\n                        }\n                    }\n                }\n            }\n        }\n        long long ans = LLONG_MAX;\n        for (int i = 0; i < N; i++) {\n            ans = (ans < dp[i]) ? ans : dp[i];\n        }\n        printf(\"%lld\\n\", ans);\n    }\n    return 0;\n}",
      "C++": "#include <iostream>\n#include <climits>\nusing namespace std;\nint main() {\n    int T;\n    cin >> T;\n    while (T--) {\n        int N, B, C;\n        cin >> N >> B >> C;\n        int A[N];\n        for (int i = 0; i < N; i++) {\n            cin >> A[i];\n        }\n        long long dp[N];\n        for (int i = 0; i < N; i++) {\n            dp[i] = LLONG_MAX;\n        }\n        dp[C - 1] = 0;\n        for (int i = 0; i < B; i++) {\n            for (int j = 0; j < N; j++) {\n                if (dp[j] != LLONG_MAX) {\n                    for (int k = 0; k < N; k++) {\n                        if (A[k] >= A[j] - i - 1 && A[k] <= A[j] + i + 1) {\n                            dp[k] = (dp[k] < dp[j] + (i + 1) * (i + 1)) ? dp[k] : dp[j] + (i + 1) * (i + 1);\n                        }\n                    }\n                }\n            }\n        }\n        long long ans = LLONG_MAX;\n        for (int i = 0; i < N; i++) {\n            ans = (ans < dp[i]) ? ans : dp[i];\n        }\n        cout << ans << endl;\n    }\n    return 0;\n}",
      "Java": "import java.util.Scanner;\npublic class Main {\n    public static void main(String[] args) {\n        Scanner sc = new Scanner(System.in);\n        int T = sc.nextInt();\n        while (T-- > 0) {\n            int N = sc.nextInt();\n            int B = sc.nextInt();\n            int C = sc.nextInt();\n            int[] A = new int[N];\n            for (int i = 0; i < N; i++) {\n                A[i] = sc.nextInt();\n            }\n            long[] dp = new long[N];\n            for (int i = 0; i < N; i++) {\n                dp[i] = Long.MAX_VALUE;\n            }\n            dp[C - 1] = 0;\n            for (int i = 0; i < B; i++) {\n                for (int j = 0; j < N; j++) {\n                    if (dp[j] != Long.MAX_VALUE) {\n                        for (int k = 0; k < N; k++) {\n                            if (A[k] >= A[j] - i - 1 && A[k] <= A[j] + i + 1) {\n                                dp[k] = (dp[k] < dp[j] + (i + 1) * (i + 1)) ? dp[k] : dp[j] + (i + 1) * (i + 1);\n                            }\n                        }\n                    }\n                }\n            }\n            long ans = Long.MAX_VALUE;\n            for (int i = 0; i < N; i++) {\n                ans = (ans < dp[i]) ? ans : dp[i];\n            }\n            System.out.println(ans);\n        }\n    }\n}",
      "Python3": "import sys\ninput = sys.stdin.readline\nT = int(input())\nfor _ in range(T):\n    N, B, C = map(int, input().split())\n    A = list(map(int, input().split()))\n    dp = [float('inf')] * N\n    dp[C - 1] = 0\n    for i in range(B):\n        for j in range(N):\n            if dp[j] != float('inf'):\n                for k in range(N):\n                    if A[k] >= A[j] - i - 1 and A[k] <= A[j] + i + 1:\n                        dp[k] = min(dp[k], dp[j] + (i + 1) * (i + 1))\n    ans = float('inf')\n    for i in range(N):\n        ans = min(ans, dp[i])\n    print(ans)",
      "JavaScript": "const fs = require('fs');\nconst lines = fs.readFileSync(0, 'utf-8').trim().split('\\n');\nlet idx = 0;\nconst readline = () => lines[idx++];\nconst T = parseInt(readline());\nfor (let i = 0; i < T; i++) {\n    const [N, B, C] = readline().split(' ').map(Number);\n    const A = readline().split(' ').map(Number);\n    const dp = new Array(N).fill(Infinity);\n    dp[C - 1] = 0;\n    for (let j = 0; j < B; j++) {\n        for (let k = 0; k < N; k++) {\n            if (dp[k] !== Infinity) {\n                for (let l = 0; l < N; l++) {\n                    if (A[l] >= A[k] - j - 1 && A[l] <= A[k] + j + 1) {\n                        dp[l] = Math.min(dp[l], dp[k] + (j + 1) * (j + 1));\n                    }\n                }\n            }\n        }\n    }\n    let ans = Infinity;\n    for (let j = 0; j < N; j++) {\n        ans = Math.min(ans, dp[j]);\n    }\n    console.log(ans);\n}"
    }
  },
  "QBCategory": "CCD",
  "boilerPlates": {
    "C": "#include <stdio.h>\n\nint main() {\n    // your code goes here\n    return 0;\n}",
    "C++": "#include <iostream>\nusing namespace std;\n\nint main() {\n    // your code goes here\n    return 0;\n}",
    "Java": "import java.util.*;\nimport java.io.*;\n\npublic class Main {\n    public static void main(String[] args) throws IOException {\n        // your code goes here\n    }\n}",
    "Python3": "# your code goes here\n",
    "JavaScript": "// your code goes here\n"
  },
  "_internal": {
    "methodName": "",
    "params": []
  }
}