{
  "questionId": "AVGPROBLEM",
  "title": "Greater Average",
  "slug": "avgproblem",
  "version": 1,
  "createdAt": "2026-07-13",
  "updatedAt": "2026-07-13",
  "source": {
    "platform": "SEED-IT",
    "courseSlug": "logical-problems",
    "contestCode": "DIFF800",
    "module": "500 to 800 difficulty rating problems",
    "submodule": "500 to 800 difficulty rating problems",
    "contentType": "default",
    "originalUrl": "https://www.codechef.com/learn/course/logical-problems/DIFF800/problems/AVGPROBLEM"
  },
  "metadata": {
    "category": "Practice",
    "difficulty": "Beginner",
    "isPremium": false,
    "tags": [
      "c++"
    ],
    "companyTags": [],
    "topicTags": [
      "500 to 800 difficulty rating problems",
      "500 to 800 difficulty rating problems"
    ],
    "QBCategory": "SEED-IT"
  },
  "content": {
    "problemStatement": "You are given $3$ numbers $A, B,$ and $C$.\n\nDetermine whether the **average** of $A$ and $B$ is **strictly greater** than $C$ or not?\n\n**NOTE:** Average of $A$ and $B$ is defined as $\\frac{(A+B)}{2}$. For example, average of $5$ and $9$ is $7$, average of $5$ and $8$ is $6.5$.",
    "constraints": [
      "- $1 \\leq T \\leq 1000$\n- $1 \\leq A, B, C \\leq 10$"
    ],
    "inputFormat": "- The first line of input will contain a single integer $T$, denoting the number of test cases.\n- Each test case consists of $3$ integers $A, B,$ and $C$.",
    "outputFormat": "For each test case, output `YES` if average of $A$ and $B$ is strictly greater than $C$, `NO` otherwise.\n\nYou may print each character of the string in uppercase or lowercase (for example, the strings `YeS`, `yEs`, `yes` and `YES` will all be treated as identical).",
    "sampleTestCases": [
      {
        "input": "5\n5 9 6\n5 8 6\n5 7 6\n4 9 8\n3 7 2\n",
        "output": "YES\nYES\nNO\nNO\nYES\n",
        "explanation": "**Test case $1$:** The average value of $5$ and $9$ is $7$ which is strictly greater than $6$.\n\n**Test case $2$:** The average value of $5$ and $8$ is $6.5$ which is strictly greater than $6$.\n\n**Test case $3$:** The average value of $5$ and $7$ is $6$ which is not strictly greater than $6$.\n\n**Test case $4$:** The average value of $4$ and $9$ is $6.5$ which is not strictly greater than $8$.\n\n**Test case $5$:** The average value of $3$ and $7$ is $5$ which is strictly greater than $2$."
      }
    ]
  },
  "testCases": {
    "hidden": [
      {
        "id": "tc_1",
        "input": "",
        "expectedOutput": "expected",
        "weight": 100
      }
    ],
    "totalTestCases": 1,
    "totalWeight": 100
  },
  "scoring": {
    "defaultScoringType": "PARTIAL_SCORE",
    "testCaseWeights": [
      100
    ],
    "maxScore": 100
  },
  "judging": {
    "timeLimitMs": 1000,
    "memoryLimitMb": 256,
    "supportedLanguages": [
      "C",
      "C++",
      "Java",
      "Python3",
      "JavaScript"
    ]
  },
  "boilerPlates": {
    "C": "#include <stdio.h>\n\nint main() {\n    // Write your C code here\n    return 0;\n}",
    "C++": "#include <iostream>\nusing namespace std;\n\nint main() {\n    // Write your C++ code here\n    return 0;\n}",
    "Java": "import java.util.*;\nimport java.io.*;\n\npublic class Main {\n    public static void main(String[] args) {\n        // Write your Java code here\n    }\n}",
    "Python3": "# Write your Python code here\n"
  }
}